[
    {
        "name": "Muz Yerli Kg",
        "url": "https://www.migros.com.tr/muz-yerli-kg-p-1a01b70",
        "price": "86,95 TL",
        "market": "Migros"
    },
    {
        "name": "Domates Pembe Kg",
        "url": "https://www.migros.com.tr/domates-pembe-kg-p-1ac9aca",
        "price": "69,95 TL",
        "market": "Migros"
    },
    {
        "name": "Limon Kg",
        "url": "https://www.migros.com.tr/limon-kg-p-19ff462",
        "price": "44,95 TL",
        "market": "Migros"
    },
    {
        "name": "Hıyar Badem Paket Kg",
        "url": "https://www.migros.com.tr/hiyar-badem-paket-kg-p-1ad3add",
        "price": "99,95 TL",
        "market": "Migros"
    },
    {
        "name": "Maydanoz Adet",
        "url": "https://www.migros.com.tr/maydanoz-adet-p-1af36a9",
        "price": "17,95 TL",
        "market": "Migros"
    },
    {
        "name": "Kabak Sakız Kg",
        "url": "https://www.migros.com.tr/kabak-sakiz-kg-p-1adb000",
        "price": "72,95 TL",
        "market": "Migros"
    },
    {
        "name": "Domates Kokteyl Kg",
        "url": "https://www.migros.com.tr/domates-kokteyl-kg-p-1aca278",
        "price": "89,95 TL",
        "market": "Migros"
    },
    {
        "name": "Hıyar Kg",
        "url": "https://www.migros.com.tr/hiyar-kg-p-1ad3ad0",
        "price": "84,95 TL",
        "market": "Migros"
    },
    {
        "name": "Domates Salkım Kg",
        "url": "https://www.migros.com.tr/domates-salkim-kg-p-1ac92d8",
        "price": "69,95 TL",
        "market": "Migros"
    },
    {
        "name": "Roka Demet",
        "url": "https://www.migros.com.tr/roka-demet-p-1b06f29",
        "price": "22,95 TL",
        "market": "Migros"
    },
    {
        "name": "Dereotu Adet",
        "url": "https://www.migros.com.tr/dereotu-adet-p-1ac2969",
        "price": "22,95 TL",
        "market": "Migros"
    },
    {
        "name": "Avokado Adet",
        "url": "https://www.migros.com.tr/avokado-adet-p-1ab6614",
        "price": "49,95 TL",
        "market": "Migros"
    },
    {
        "name": "Biber Kırmızı Kg",
        "url": "https://www.migros.com.tr/biber-kirmizi-kg-p-1ac0e08",
        "price": "114,95 TL",
        "market": "Migros"
    },
    {
        "name": "Havuç Beypazarı Paket Kg",
        "url": "https://www.migros.com.tr/havuc-beypazari-paket-kg-p-1ad36f9",
        "price": "52,95 TL",
        "market": "Migros"
    },
    {
        "name": "Atom Salata Adet",
        "url": "https://www.migros.com.tr/atom-salata-adet-p-1b0e460",
        "price": "44,95 TL",
        "market": "Migros"
    },
    {
        "name": "Domates Kg",
        "url": "https://www.migros.com.tr/domates-kg-p-1ac7780",
        "price": "54,90 TL",
        "market": "Migros"
    },
    {
        "name": "Ceviz Kabuklu Kg",
        "url": "https://www.migros.com.tr/ceviz-kabuklu-kg-p-19ce720",
        "price": "149,95 TL",
        "market": "Migros"
    },
    {
        "name": "Salata Kıvırcık Adet",
        "url": "https://www.migros.com.tr/salata-kivircik-adet-p-1b0bd99",
        "price": "42,95 TL",
        "market": "Migros"
    },
    {
        "name": "Biber Çarliston Kg",
        "url": "https://www.migros.com.tr/biber-carliston-kg-p-1ac0638",
        "price": "94,95 TL",
        "market": "Migros"
    },
    {
        "name": "Yaban Mersini 125 G",
        "url": "https://www.migros.com.tr/yaban-mersini-125-g-p-1a4e9f4",
        "price": "99,95 TL",
        "market": "Migros"
    },
    {
        "name": "Soğan Taze Demet",
        "url": "https://www.migros.com.tr/sogan-taze-demet-p-1b145fa",
        "price": "56,95 TL",
        "market": "Migros"
    },
    {
        "name": "Çilek Kg",
        "url": "https://www.migros.com.tr/cilek-kg-p-19d3928",
        "price": "194,95 TL",
        "market": "Migros"
    },
    {
        "name": "Elma Starking Kg",
        "url": "https://www.migros.com.tr/elma-starking-kg-p-19e0c18",
        "price": "59,95 TL",
        "market": "Migros"
    },
    {
        "name": "Muz İthal Kg",
        "url": "https://www.migros.com.tr/muz-ithal-kg-p-1a01f58",
        "price": "109,95 TL",
        "market": "Migros"
    },
    {
        "name": "Elma Granny Smith Kg",
        "url": "https://www.migros.com.tr/elma-granny-smith-kg-p-19e0448",
        "price": "69,95 TL",
        "market": "Migros"
    },
    {
        "name": "Nane Adet",
        "url": "https://www.migros.com.tr/nane-adet-p-1af84c9",
        "price": "24,95 TL",
        "market": "Migros"
    },
    {
        "name": "Biber Dolmalık Kg",
        "url": "https://www.migros.com.tr/biber-dolmalik-kg-p-1ac0a20",
        "price": "Fiyat bulunamadı",
        "market": "Migros"
    },
    {
        "name": "Portakal Kg",
        "url": "https://www.migros.com.tr/portakal-kg-p-1a0a047",
        "price": "54,95 TL",
        "market": "Migros"
    },
    {
        "name": "Elma Pink Lady Kg",
        "url": "https://www.migros.com.tr/elma-pink-lady-kg-p-19e1c40",
        "price": "59,95 TL",
        "market": "Migros"
    },
    {
        "name": "Portakal Sıkma File Kg",
        "url": "https://www.migros.com.tr/portakal-sikma-file-kg-p-1a090a1",
        "price": "49,95 TL",
        "market": "Migros"
    },
    {
        "name": "Havuç Çıtır 250 G Paket Adet",
        "url": "https://www.migros.com.tr/havuc-citir-250-g-paket-adet-p-1ad13e4",
        "price": "22,95 TL",
        "market": "Migros"
    },
    {
        "name": "Biber Köy Usulü Kg",
        "url": "https://www.migros.com.tr/biber-koy-usulu-kg-p-1ac1258",
        "price": "119,95 TL",
        "market": "Migros"
    },
    {
        "name": "Bakla Sakız Kg",
        "url": "https://www.migros.com.tr/bakla-sakiz-kg-p-1ab8d20",
        "price": "139,95 TL",
        "market": "Migros"
    },
    {
        "name": "Ananas Adet",
        "url": "https://www.migros.com.tr/ananas-adet-p-1a3a1cb",
        "price": "99,95 TL",
        "market": "Migros"
    },
    {
        "name": "Migros Pırasa Paket Kg",
        "url": "https://www.migros.com.tr/migros-pirasa-paket-kg-p-1b05449",
        "price": "52,95 TL",
        "market": "Migros"
    },
    {
        "name": "Armut Santa Maria Kg",
        "url": "https://www.migros.com.tr/armut-santa-maria-kg-p-19c6a20",
        "price": "72,95 TL",
        "market": "Migros"
    },
    {
        "name": "Pancar Kg",
        "url": "https://www.migros.com.tr/pancar-kg-p-1b10bc3",
        "price": "54,95 TL",
        "market": "Migros"
    },
    {
        "name": "Lahana Kırmızı Kg",
        "url": "https://www.migros.com.tr/lahana-kirmizi-kg-p-1aec179",
        "price": "74,95 TL",
        "market": "Migros"
    },
    {
        "name": "Patates Taze Mini Kg",
        "url": "https://www.migros.com.tr/patates-taze-mini-kg-p-1afb3a0",
        "price": "54,95 TL",
        "market": "Migros"
    },
    {
        "name": "Turp Kırmızı Demet",
        "url": "https://www.migros.com.tr/turp-kirmizi-demet-p-1b26afa",
        "price": "39,95 TL",
        "market": "Migros"
    },
    {
        "name": "Elma Amasya Kg",
        "url": "https://www.migros.com.tr/elma-amasya-kg-p-19dfc78",
        "price": "89,95 TL",
        "market": "Migros"
    },
    {
        "name": "Elma Golden Kg",
        "url": "https://www.migros.com.tr/elma-golden-kg-p-19e0830",
        "price": "59,95 TL",
        "market": "Migros"
    },
    {
        "name": "Eurofresh Yıkanmış Hazır Ispanak 700 G",
        "url": "https://www.migros.com.tr/eurofresh-yikanmis-hazir-ispanak-700-g-p-1b10a34",
        "price": "93,95 TL",
        "market": "Migros"
    },
    {
        "name": "Elma Fuji Kg",
        "url": "https://www.migros.com.tr/elma-fuji-kg-p-19e0a30",
        "price": "49,95 TL",
        "market": "Migros"
    },
    {
        "name": "Pazı Demet",
        "url": "https://www.migros.com.tr/pazi-demet-p-1b02105",
        "price": "44,95 TL",
        "market": "Migros"
    },
    {
        "name": "Zencefil Kg",
        "url": "https://www.migros.com.tr/zencefil-kg-p-1b466c1",
        "price": "249,95 TL",
        "market": "Migros"
    },
    {
        "name": "Mantar İstridye 200 G",
        "url": "https://www.migros.com.tr/mantar-istridye-200-g-p-1af04a3",
        "price": "69,95 TL",
        "market": "Migros"
    },
    {
        "name": "Marul Adet",
        "url": "https://www.migros.com.tr/marul-adet-p-1af0f99",
        "price": "59,95 TL",
        "market": "Migros"
    },
    {
        "name": "Spesiyal Soğan File Kg",
        "url": "https://www.migros.com.tr/spesiyal-sogan-file-kg-p-1b1b995",
        "price": "39,95 TL",
        "market": "Migros"
    },
    {
        "name": "Yerli Papaya",
        "url": "https://www.migros.com.tr/yerli-papaya-p-1a43a23",
        "price": "79,95 TL",
        "market": "Migros"
    },
    {
        "name": "Brokoli Kg",
        "url": "https://www.migros.com.tr/brokoli-kg-p-1adfe20",
        "price": "79,95 TL",
        "market": "Migros"
    },
    {
        "name": "Eurofresh Yıkanmış Kıvırcık Marul 150 Gr",
        "url": "https://www.migros.com.tr/eurofresh-yikanmis-kivircik-marul-150-gr-p-1af1b6f",
        "price": "39,95 TL",
        "market": "Migros"
    },
    {
        "name": "Eurofresh Doğranmış Göbek Salata (Parça) 200G",
        "url": "https://www.migros.com.tr/eurofresh-dogranmis-gobek-salata-parca-200g-p-1b10a32",
        "price": "49,95 TL",
        "market": "Migros"
    },
    {
        "name": "Ispanak Kg",
        "url": "https://www.migros.com.tr/ispanak-kg-p-1ad6243",
        "price": "72,95 TL",
        "market": "Migros"
    },
    {
        "name": "Erüst Mini Mini Domates 250 G",
        "url": "https://www.migros.com.tr/erust-mini-mini-domates-250-g-p-1ac9b27",
        "price": "64,95 TL",
        "market": "Migros"
    },
    {
        "name": "Eurofresh Doğranmış Kırmızı Lahana 300 Gr",
        "url": "https://www.migros.com.tr/eurofresh-dogranmis-kirmizi-lahana-300-gr-p-1aec952",
        "price": "59,95 TL",
        "market": "Migros"
    },
    {
        "name": "Greyfurt Kan Kg",
        "url": "https://www.migros.com.tr/greyfurt-kan-kg-p-19e7590",
        "price": "39,95 TL",
        "market": "Migros"
    },
    {
        "name": "Biber Acı Şili Kırmızı Kg",
        "url": "https://www.migros.com.tr/biber-aci-sili-kirmizi-kg-p-1ac25c9",
        "price": "139,95 TL",
        "market": "Migros"
    },
    {
        "name": "Nar Kg",
        "url": "https://www.migros.com.tr/nar-kg-p-1a06990",
        "price": "89,95 TL",
        "market": "Migros"
    },
    {
        "name": "Doğanay Gurme Acılı Şalgam Cam 750 Ml",
        "url": "https://www.migros.com.tr/doganay-gurme-acili-salgam-cam-750-ml-p-7ad698",
        "price": "67,50 TL",
        "market": "Migros"
    },
    {
        "name": "Doğanay Gurme Sade Şalgam Cam 750 Ml",
        "url": "https://www.migros.com.tr/doganay-gurme-sade-salgam-cam-750-ml-p-7ad699",
        "price": "67,50 TL",
        "market": "Migros"
    },
    {
        "name": "Doğanay Şalgam Suyu Acılı 1000 Ml",
        "url": "https://www.migros.com.tr/doganay-salgam-suyu-acili-1000-ml-p-7b4648",
        "price": "39,50 TL",
        "market": "Migros"
    },
    {
        "name": "Doğanay Şalgam Suyu Sade 1000 Ml",
        "url": "https://www.migros.com.tr/doganay-salgam-suyu-sade-1000-ml-p-7b4652",
        "price": "39,50 TL",
        "market": "Migros"
    },
    {
        "name": "Doğanay Acılı Şalgam Suyu Acılı 300 Ml",
        "url": "https://www.migros.com.tr/doganay-acili-salgam-suyu-acili-300-ml-p-7af81d",
        "price": "20,95 TL",
        "market": "Migros"
    },
    {
        "name": "Doğanay Şalgam Suyu Sade 300 Ml",
        "url": "https://www.migros.com.tr/doganay-salgam-suyu-sade-300-ml-p-7b463c",
        "price": "20,95 TL",
        "market": "Migros"
    },
    {
        "name": "Assu Mineralli Su 5 L",
        "url": "https://www.migros.com.tr/assu-mineralli-su-5-l-p-7afc9b",
        "price": "23,50 TL",
        "market": "Migros"
    },
    {
        "name": "Beypazarı Maden Suyu 6X200 Ml",
        "url": "https://www.migros.com.tr/beypazari-maden-suyu-6x200-ml-p-7ab106",
        "price": "37,90 TL",
        "market": "Migros"
    },
    {
        "name": "Kurukahveci Mehmet Efendi Türk Kahvesi 100 G",
        "url": "https://www.migros.com.tr/kurukahveci-mehmet-efendi-turk-kahvesi-100-g-p-310151",
        "price": "66,50 TL",
        "market": "Migros"
    },
    {
        "name": "Erikli Doğal Kaynak Suyu 6x1 L",
        "url": "https://www.migros.com.tr/erikli-dogal-kaynak-suyu-6x1-l-p-7b0507",
        "price": "116,50 TL",
        "market": "Migros"
    },
    {
        "name": "Coca-Cola Orijinal Tat Pet 1 L",
        "url": "https://www.migros.com.tr/coca-cola-orijinal-tat-pet-1-l-p-7a3bcc",
        "price": "40,00 TL",
        "market": "Migros"
    },
    {
        "name": "Hamidiye Doğal Mineralli Su 0.5 L",
        "url": "https://www.migros.com.tr/hamidiye-dogal-mineralli-su-05-l-p-7afcba",
        "price": "3,95 TL",
        "market": "Migros"
    },
    {
        "name": "Hamidiye Doğal Mineralli Su 1.5 L",
        "url": "https://www.migros.com.tr/hamidiye-dogal-mineralli-su-15-l-p-7afcbb",
        "price": "7,95 TL",
        "market": "Migros"
    },
    {
        "name": "Coca-Cola Zero Sugar Pet 1 L",
        "url": "https://www.migros.com.tr/coca-cola-zero-sugar-pet-1-l-p-7a3bcd",
        "price": "40,00 TL",
        "market": "Migros"
    },
    {
        "name": "Erikli Doğal Kaynak Suyu 12x500 Ml",
        "url": "https://www.migros.com.tr/erikli-dogal-kaynak-suyu-12x500-ml-p-7afc7c",
        "price": "138,75 TL",
        "market": "Migros"
    },
    {
        "name": "Hamidiye Kaynak Suyu 5 L Pet",
        "url": "https://www.migros.com.tr/hamidiye-kaynak-suyu-5-l-pet-p-7a8047",
        "price": "23,50 TL",
        "market": "Migros"
    },
    {
        "name": "Sırma Doğal Maden Suyu 6x200 Ml Cam",
        "url": "https://www.migros.com.tr/sirma-dogal-maden-suyu-6x200-ml-cam-p-7ab1c4",
        "price": "47,50 TL",
        "market": "Migros"
    },
    {
        "name": "Sütaş Pratik Şişe Ayran 2 L",
        "url": "https://www.migros.com.tr/sutas-pratik-sise-ayran-2-l-p-b03f09",
        "price": "69,95 TL",
        "market": "Migros"
    },
    {
        "name": "Uludağ Doğal Maden Suyu 6X200 Ml",
        "url": "https://www.migros.com.tr/uludag-dogal-maden-suyu-6x200-ml-p-7ab0ca",
        "price": "49,90 TL",
        "market": "Migros"
    },
    {
        "name": "Migros Ayran 1500 Ml",
        "url": "https://www.migros.com.tr/migros-ayran-1500-ml-p-b061d0",
        "price": "Fiyat bulunamadı",
        "market": "Migros"
    },
    {
        "name": "Lipton Ice Tea Şeftali Aromalı 1,5 L",
        "url": "https://www.migros.com.tr/lipton-ice-tea-seftali-aromali-15-l-p-7afacc",
        "price": "45,00 TL",
        "market": "Migros"
    },
    {
        "name": "Sütaş Pratik Şişe Ayran 1 L",
        "url": "https://www.migros.com.tr/sutas-pratik-sise-ayran-1-l-p-b03f06",
        "price": "36,75 TL",
        "market": "Migros"
    },
    {
        "name": "Altınkılıç Kefir 1 L",
        "url": "https://www.migros.com.tr/altinkilic-kefir-1-l-p-b040b4",
        "price": "66,50 TL",
        "market": "Migros"
    },
    {
        "name": "Saka Doğal Mineralli Su 5 L",
        "url": "https://www.migros.com.tr/saka-dogal-mineralli-su-5-l-p-7b081d",
        "price": "39,75 TL",
        "market": "Migros"
    },
    {
        "name": "Assu Mineralli Su 0.5 L",
        "url": "https://www.migros.com.tr/assu-mineralli-su-05-l-p-7afc99",
        "price": "3,95 TL",
        "market": "Migros"
    },
    {
        "name": "Nescafe 3'ü 1 Arada 17.5 G x 15'li",
        "url": "https://www.migros.com.tr/nescafe-3u-1-arada-175-g-x-15li-p-312c7b",
        "price": "99,95 TL",
        "market": "Migros"
    },
    {
        "name": "Altınkılıç Laktozsuz Kefir 1 L",
        "url": "https://www.migros.com.tr/altinkilic-laktozsuz-kefir-1-l-p-b04113",
        "price": "73,50 TL",
        "market": "Migros"
    },
    {
        "name": "Kızılay Erzincan Doğal Maden Suyu 6X200 Ml",
        "url": "https://www.migros.com.tr/kizilay-erzincan-dogal-maden-suyu-6x200-ml-p-87cde5",
        "price": "37,90 TL",
        "market": "Migros"
    },
    {
        "name": "Saka Doğal Mineralli Su 6x1 L",
        "url": "https://www.migros.com.tr/saka-dogal-mineralli-su-6x1-l-p-7afcd3",
        "price": "106,50 TL",
        "market": "Migros"
    },
    {
        "name": "Uludağ Limonata Şekersiz 1 L",
        "url": "https://www.migros.com.tr/uludag-limonata-sekersiz-1-l-p-7afd0c",
        "price": "Fiyat bulunamadı",
        "market": "Migros"
    },
    {
        "name": "Assu Mineralli Su 1.5 L",
        "url": "https://www.migros.com.tr/assu-mineralli-su-15-l-p-7afc9a",
        "price": "7,95 TL",
        "market": "Migros"
    },
    {
        "name": "Coca-Cola Orijinal Tat Pet 1,5 L",
        "url": "https://www.migros.com.tr/coca-cola-orijinal-tat-pet-15-l-p-7a3c97",
        "price": "45,00 TL",
        "market": "Migros"
    },
    {
        "name": "Sprite Limon Aromalı Gazoz Kutu 6 x 250 Ml",
        "url": "https://www.migros.com.tr/sprite-limon-aromali-gazoz-kutu-6-x-250-ml-p-7a9abe",
        "price": "Fiyat bulunamadı",
        "market": "Migros"
    },
    {
        "name": "Coca-Cola Orijinal Tat Pet 4x1 L",
        "url": "https://www.migros.com.tr/coca-cola-orijinal-tat-pet-4x1-l-p-7a3c99",
        "price": "153,50 TL",
        "market": "Migros"
    },
    {
        "name": "Erikli Doğal Kaynak Suyu 5L Pet Şişe",
        "url": "https://www.migros.com.tr/erikli-dogal-kaynak-suyu-5l-pet-sise-p-7b04fb",
        "price": "49,50 TL",
        "market": "Migros"
    },
    {
        "name": "Fanta Portakal Aromalı Pet 1 L",
        "url": "https://www.migros.com.tr/fanta-portakal-aromali-pet-1-l-p-7a67f0",
        "price": "40,00 TL",
        "market": "Migros"
    },
    {
        "name": "Saka Doğal Maden Suyu 6X200 Ml",
        "url": "https://www.migros.com.tr/saka-dogal-maden-suyu-6x200-ml-p-7aae79",
        "price": "44,00 TL",
        "market": "Migros"
    },
    {
        "name": "Pepsi Kola Pet 4 x 1 L",
        "url": "https://www.migros.com.tr/pepsi-kola-pet-4-x-1-l-p-7a3d5d",
        "price": "145,95 TL",
        "market": "Migros"
    },
    {
        "name": "Doğuş Tiryaki Çay 1000 G",
        "url": "https://www.migros.com.tr/dogus-tiryaki-cay-1000-g-p-2f93b4",
        "price": "185,00 TL",
        "market": "Migros"
    },
    {
        "name": "Kızılay Afyonkarahisar Doğal Maden Suyu 6x200 Ml",
        "url": "https://www.migros.com.tr/kizilay-afyonkarahisar-dogal-maden-suyu-6x200-ml-p-7ab0cf",
        "price": "37,90 TL",
        "market": "Migros"
    },
    {
        "name": "Erikli Doğal Kaynak Suyu 10L Pet Şişe",
        "url": "https://www.migros.com.tr/erikli-dogal-kaynak-suyu-10l-pet-sise-p-7b04fd",
        "price": "88,95 TL",
        "market": "Migros"
    },
    {
        "name": "Lipton Ice Tea Mango Pet 1,5 L",
        "url": "https://www.migros.com.tr/lipton-ice-tea-mango-pet-15-l-p-7afac9",
        "price": "45,00 TL",
        "market": "Migros"
    },
    {
        "name": "Starbucks White Mocha Kahve Karışımı 24 G",
        "url": "https://www.migros.com.tr/starbucks-white-mocha-kahve-karisimi-24-g-p-31a153",
        "price": "22,95 TL",
        "market": "Migros"
    },
    {
        "name": "Nescafé Gold Ekonomik Paket 180 G",
        "url": "https://www.migros.com.tr/nescaf-gold-ekonomik-paket-180-g-p-314f75",
        "price": "289,50 TL",
        "market": "Migros"
    },
    {
        "name": "Çaykur Tiryaki Çayı 1000 G",
        "url": "https://www.migros.com.tr/caykur-tiryaki-cayi-1000-g-p-2f7993",
        "price": "232,00 TL",
        "market": "Migros"
    },
    {
        "name": "Coca-Cola Zero Sugar Pet 1,5 L",
        "url": "https://www.migros.com.tr/coca-cola-zero-sugar-pet-15-l-p-7a3c98",
        "price": "45,00 TL",
        "market": "Migros"
    },
    {
        "name": "Nestlé Pure Life Doğal Kaynak Suyu 5 lt Pet",
        "url": "https://www.migros.com.tr/nestl-pure-life-dogal-kaynak-suyu-5-lt-pet-p-7b02d9",
        "price": "48,95 TL",
        "market": "Migros"
    },
    {
        "name": "Doğanay Şalgam Suyu Sade 1000 Ml",
        "url": "https://www.migros.com.tr/doganay-salgam-suyu-sade-1000-ml-p-7b4652",
        "price": "39,50 TL",
        "market": "Migros"
    },
    {
        "name": "Pepsi Özel Kutu 4 x 250 Ml",
        "url": "https://www.migros.com.tr/pepsi-ozel-kutu-4-x-250-ml-p-7a3a47",
        "price": "126,00 TL",
        "market": "Migros"
    },
    {
        "name": "Pepsi Zero Sugar Kola Pet 4 x 1 L",
        "url": "https://www.migros.com.tr/pepsi-zero-sugar-kola-pet-4-x-1-l-p-7a3d8e",
        "price": "145,95 TL",
        "market": "Migros"
    },
    {
        "name": "Lipton Ice Tea Limon Aromalı 1,5 L",
        "url": "https://www.migros.com.tr/lipton-ice-tea-limon-aromali-15-l-p-7afacb",
        "price": "45,00 TL",
        "market": "Migros"
    },
    {
        "name": "Starbucks Caffe Latte Premium Kahve Karışımı 18 G",
        "url": "https://www.migros.com.tr/starbucks-caffe-latte-premium-kahve-karisimi-18-g-p-31a14d",
        "price": "22,95 TL",
        "market": "Migros"
    },
    {
        "name": "Çamlıca Limon Aromalı Gazoz 1 L",
        "url": "https://www.migros.com.tr/camlica-limon-aromali-gazoz-1-l-p-7a9bb2",
        "price": "31,50 TL",
        "market": "Migros"
    },
    {
        "name": "Eker Ayran 1,5 L",
        "url": "https://www.migros.com.tr/eker-ayran-15-l-p-b0475c",
        "price": "65,00 TL",
        "market": "Migros"
    },
    {
        "name": "Cappy Pulpy Portakallı İçecek Pet 1 L",
        "url": "https://www.migros.com.tr/cappy-pulpy-portakalli-icecek-pet-1-l-p-7ae752",
        "price": "56,00 TL",
        "market": "Migros"
    },
    {
        "name": "Cappy Geleneksel Limonata Pet 1 L",
        "url": "https://www.migros.com.tr/cappy-geleneksel-limonata-pet-1-l-p-7ae742",
        "price": "38,00 TL",
        "market": "Migros"
    },
    {
        "name": "Coca-Cola Light Pet 1 L",
        "url": "https://www.migros.com.tr/coca-cola-light-pet-1-l-p-7a3c95",
        "price": "40,00 TL",
        "market": "Migros"
    },
    {
        "name": "Starbucks Caffe Mocha Premium Kahve Karışımı 22 G",
        "url": "https://www.migros.com.tr/starbucks-caffe-mocha-premium-kahve-karisimi-22-g-p-31a150",
        "price": "22,95 TL",
        "market": "Migros"
    },
    {
        "name": "Monster Ultra Şekersiz Enerji İçeceği Kutu 500 ML",
        "url": "https://www.migros.com.tr/monster-ultra-sekersiz-enerji-icecegi-kutu-500-ml-p-7bcbff",
        "price": "50,00 TL",
        "market": "Migros"
    },
    {
        "name": "Beypazarı Premium Sade Doğal Maden Suyu 750 Ml",
        "url": "https://www.migros.com.tr/beypazari-premium-sade-dogal-maden-suyu-750-ml-p-7aaec6",
        "price": "34,95 TL",
        "market": "Migros"
    },
    {
        "name": "Migros Filiz Siyah Çay 1000 G",
        "url": "https://www.migros.com.tr/migros-filiz-siyah-cay-1000-g-p-2f9638",
        "price": "135,00 TL",
        "market": "Migros"
    },
    {
        "name": "Coca-Cola Orijinal Tat Daha Az Kalori Pet 2,5 L",
        "url": "https://www.migros.com.tr/coca-cola-orijinal-tat-daha-az-kalori-pet-25-l-p-7a5cdb",
        "price": "60,00 TL",
        "market": "Migros"
    },
    {
        "name": "Erikli Doğal Kaynak Suyu 6x1.5 L",
        "url": "https://www.migros.com.tr/erikli-dogal-kaynak-suyu-6x15-l-p-7b0508",
        "price": "125,95 TL",
        "market": "Migros"
    },
    {
        "name": "Nescafé Classic Ekonomik Paket 100 G",
        "url": "https://www.migros.com.tr/nescaf-classic-ekonomik-paket-100-g-p-31273d",
        "price": "120,00 TL",
        "market": "Migros"
    },
    {
        "name": "Doğanay Şalgam Suyu Acılı 1000 Ml",
        "url": "https://www.migros.com.tr/doganay-salgam-suyu-acili-1000-ml-p-7b4648",
        "price": "39,50 TL",
        "market": "Migros"
    },
    {
        "name": "Sırma C+ Limon Aromalı 6x200 Ml",
        "url": "https://www.migros.com.tr/sirma-c-limon-aromali-6x200-ml-p-7aaecd",
        "price": "53,00 TL",
        "market": "Migros"
    },
    {
        "name": "Cif Sprey Ultra Anında Etki Kir ve Yağ Çözücü 1025 Ml",
        "url": "https://www.migros.com.tr/cif-sprey-ultra-aninda-etki-kir-ve-yag-cozucu-1025-ml-p-1dc14b0",
        "price": "Fiyat bulunamadı",
        "market": "Migros"
    },
    {
        "name": "Cif Sprey Power & Shine Banyo 750 Ml",
        "url": "https://www.migros.com.tr/cif-sprey-power-shine-banyo-750-ml-p-1d4f3b3",
        "price": "114,95 TL",
        "market": "Migros"
    },
    {
        "name": "Cif Sprey Power & Shine Mutfak 750 Ml",
        "url": "https://www.migros.com.tr/cif-sprey-power-shine-mutfak-750-ml-p-1d4f3b4",
        "price": "114,95 TL",
        "market": "Migros"
    },
    {
        "name": "Sleepy Yüzey Temizlik Havlusu Beyaz Sabun 100'lü",
        "url": "https://www.migros.com.tr/sleepy-yuzey-temizlik-havlusu-beyaz-sabun-100lu-p-1db8525",
        "price": "133,50 TL",
        "market": "Migros"
    },
    {
        "name": "Migros Ekonomik Orta Boy Çöp Torbası 30'lu",
        "url": "https://www.migros.com.tr/migros-ekonomik-orta-boy-cop-torbasi-30lu-p-1dc13b1",
        "price": "28,95 TL",
        "market": "Migros"
    },
    {
        "name": "Migros Ultra Çamaşır Suyu Fresh 1000 Ml",
        "url": "https://www.migros.com.tr/migros-ultra-camasir-suyu-fresh-1000-ml-p-1d2749a",
        "price": "34,95 TL",
        "market": "Migros"
    },
    {
        "name": "Migros Ekonomik Çöp Torbası Büyük Boy 20 Adet",
        "url": "https://www.migros.com.tr/migros-ekonomik-cop-torbasi-buyuk-boy-20-adet-p-1dc27e4",
        "price": "34,95 TL",
        "market": "Migros"
    },
    {
        "name": "Domestos Çamaşır Suyu Çam Ferahlığı 3.240 ML",
        "url": "https://www.migros.com.tr/domestos-camasir-suyu-cam-ferahligi-3240-ml-p-1d274e0",
        "price": "169,95 TL",
        "market": "Migros"
    },
    {
        "name": "Asperox Sarı Güç Sprey 1 L",
        "url": "https://www.migros.com.tr/asperox-sari-guc-sprey-1-l-p-1d4f3c4",
        "price": "99,95 TL",
        "market": "Migros"
    },
    {
        "name": "Sleepy Yüzey Temizlik Havlusu Çamaşır Sulu 100'lü",
        "url": "https://www.migros.com.tr/sleepy-yuzey-temizlik-havlusu-camasir-sulu-100lu-p-1db76e3",
        "price": "133,50 TL",
        "market": "Migros"
    },
    {
        "name": "Migros Ekonomik Küçük Boy Çöp Torbası 40 Adet",
        "url": "https://www.migros.com.tr/migros-ekonomik-kucuk-boy-cop-torbasi-40-adet-p-1dc13b0",
        "price": "24,95 TL",
        "market": "Migros"
    },
    {
        "name": "Selsil Pak Genel Amaçlı Mucize Temizleyici 500 G",
        "url": "https://www.migros.com.tr/selsil-pak-genel-amacli-mucize-temizleyici-500-g-p-1ddd6cd",
        "price": "35,95 TL",
        "market": "Migros"
    },
    {
        "name": "Yumoş Sıvı Bakım Deterjanı Siyah 42 Yıkama 2520 Ml",
        "url": "https://www.migros.com.tr/yumos-sivi-bakim-deterjani-siyah-42-yikama-2520-ml-p-1d1ffe2",
        "price": "235,95 TL",
        "market": "Migros"
    },
    {
        "name": "Yumoş Bakım Deterjanı Renkli 42 Yıkama 2520 Ml",
        "url": "https://www.migros.com.tr/yumos-bakim-deterjani-renkli-42-yikama-2520-ml-p-1d1ffe0",
        "price": "235,95 TL",
        "market": "Migros"
    },
    {
        "name": "Fairy 650 ml Sıvı Bulaşık Deterjanı Limon",
        "url": "https://www.migros.com.tr/fairy-650-ml-sivi-bulasik-deterjani-limon-p-1d33814",
        "price": "84,95 TL",
        "market": "Migros"
    },
    {
        "name": "Migros Bulaşık Süngeri - Oluklu 5'Li",
        "url": "https://www.migros.com.tr/migros-bulasik-sungeri-oluklu-5li-p-1db9e3b",
        "price": "21,95 TL",
        "market": "Migros"
    },
    {
        "name": "Asperox Mavi Güç Sprey 1 L",
        "url": "https://www.migros.com.tr/asperox-mavi-guc-sprey-1-l-p-1d4ccb4",
        "price": "99,95 TL",
        "market": "Migros"
    },
    {
        "name": "Finish Ultimate Plus Hepsi 1 Arada 40 Tablet 488 G",
        "url": "https://www.migros.com.tr/finish-ultimate-plus-hepsi-1-arada-40-tablet-488-g-p-1d8b9ea",
        "price": "467,95 TL",
        "market": "Migros"
    },
    {
        "name": "Omo Active Oxygen Etkisi Sıvı Çamaşır Deterjanı Beyazlar İçin 1690 ml",
        "url": "https://www.migros.com.tr/omo-active-oxygen-etkisi-sivi-camasir-deterjani-beyazlar-icin-1690-ml-p-1cbc71a",
        "price": "267,95 TL",
        "market": "Migros"
    },
    {
        "name": "Sleepy Yüzey Temizleme Havlusu Arap Sabunlu 100'lü",
        "url": "https://www.migros.com.tr/sleepy-yuzey-temizleme-havlusu-arap-sabunlu-100lu-p-1db76e4",
        "price": "133,50 TL",
        "market": "Migros"
    },
    {
        "name": "Migros Bulaşık Makinesi Parlatıcı 500 Ml",
        "url": "https://www.migros.com.tr/migros-bulasik-makinesi-parlatici-500-ml-p-1d36072",
        "price": "24,95 TL",
        "market": "Migros"
    },
    {
        "name": "Finish Quantum Ultimate %0 21 Tablet 267 G",
        "url": "https://www.migros.com.tr/finish-quantum-ultimate-0-21-tablet-267-g-p-1d8b9e4",
        "price": "270,95 TL",
        "market": "Migros"
    },
    {
        "name": "Ariel Dağ Esintisi 3 Kg AquaPudra Toz Çamaşır Deterjanı",
        "url": "https://www.migros.com.tr/ariel-dag-esintisi-3-kg-aquapudra-toz-camasir-deterjani-p-1cbc712",
        "price": "239,95 TL",
        "market": "Migros"
    },
    {
        "name": "Pril Sıvı Bulaşık Deterjanı 4kg Limon",
        "url": "https://www.migros.com.tr/pril-sivi-bulasik-deterjani-4kg-limon-p-1d33868",
        "price": "189,95 TL",
        "market": "Migros"
    },
    {
        "name": "Porçöz Pas ve Kireç Çözücü 1 L",
        "url": "https://www.migros.com.tr/porcoz-pas-ve-kirec-cozucu-1-l-p-1ddd4eb",
        "price": "69,95 TL",
        "market": "Migros"
    },
    {
        "name": "Finish Bulaşık Makinesi Tuzu 1500 G",
        "url": "https://www.migros.com.tr/finish-bulasik-makinesi-tuzu-1500-g-p-1d081a4",
        "price": "115,95 TL",
        "market": "Migros"
    },
    {
        "name": "Domestos Çamaşır Suyu Beyaz Sabun Ferahlığı 750 Ml",
        "url": "https://www.migros.com.tr/domestos-camasir-suyu-beyaz-sabun-ferahligi-750-ml-p-1d24f34",
        "price": "57,95 TL",
        "market": "Migros"
    },
    {
        "name": "Migros Yüzey Temizleyici Beyaz Sabun Kokulu 1500Ml",
        "url": "https://www.migros.com.tr/migros-yuzey-temizleyici-beyaz-sabun-kokulu-1500ml-p-1d4be93",
        "price": "41,95 TL",
        "market": "Migros"
    },
    {
        "name": "Porçöz Lavabo Açıcı Granül 4 x 50 G",
        "url": "https://www.migros.com.tr/porcoz-lavabo-acici-granul-4-x-50-g-p-1e241c9",
        "price": "99,95 TL",
        "market": "Migros"
    },
    {
        "name": "Domestos Tuvalet Bloğu Çam Ormanı 2x50 G",
        "url": "https://www.migros.com.tr/domestos-tuvalet-blogu-cam-ormani-2x50-g-p-1ddd6c7",
        "price": "99,95 TL",
        "market": "Migros"
    },
    {
        "name": "Mr.Oxy Yüzey Temizlik Havlusu Beyaz Sabun 100'lü",
        "url": "https://www.migros.com.tr/mroxy-yuzey-temizlik-havlusu-beyaz-sabun-100lu-p-1db76fe",
        "price": "Fiyat bulunamadı",
        "market": "Migros"
    },
    {
        "name": "Peros Sıvı Bakım Renk Uzmanı Renkliler 3 L",
        "url": "https://www.migros.com.tr/peros-sivi-bakim-renk-uzmani-renkliler-3-l-p-1d1d9ff",
        "price": "249,95 TL",
        "market": "Migros"
    },
    {
        "name": "Omo Actıve Oxygen 40 Yıkama 6 Kg",
        "url": "https://www.migros.com.tr/omo-active-oxygen-40-yikama-6-kg-p-1cbc71d",
        "price": "424,95 TL",
        "market": "Migros"
    },
    {
        "name": "Migros Çöp Torbası Büzgülü Büyük Boy Limon Kokulu 15'li",
        "url": "https://www.migros.com.tr/migros-cop-torbasi-buzgulu-buyuk-boy-limon-kokulu-15li-p-1dc27e7",
        "price": "42,95 TL",
        "market": "Migros"
    },
    {
        "name": "Yumoş Extra Konsantre Çamaşır Yumuşatıcı Sakura 1440 Ml 60 Yıkama",
        "url": "https://www.migros.com.tr/yumos-extra-konsantre-camasir-yumusatici-sakura-1440-ml-60-yikama-p-1d29d61",
        "price": "176,95 TL",
        "market": "Migros"
    },
    {
        "name": "Bref Rezervuar Küpleri Okyanus 2'li",
        "url": "https://www.migros.com.tr/bref-rezervuar-kupleri-okyanus-2li-p-1ddc2bf",
        "price": "84,95 TL",
        "market": "Migros"
    },
    {
        "name": "Huub Slim Askı 10'lu",
        "url": "https://www.migros.com.tr/huub-slim-aski-10lu-p-26714fd",
        "price": "99,95 TL",
        "market": "Migros"
    },
    {
        "name": "Pril Excellence Duo Jel 900 Ml (50 Yıkama) Yağ Çözücü",
        "url": "https://www.migros.com.tr/pril-excellence-duo-jel-900-ml-50-yikama-yag-cozucu-p-1d8b9a1",
        "price": "323,95 TL",
        "market": "Migros"
    },
    {
        "name": "Migros Ultra Çamaşır Suyu Ocean 1000 Ml",
        "url": "https://www.migros.com.tr/migros-ultra-camasir-suyu-ocean-1000-ml-p-1d2749b",
        "price": "34,95 TL",
        "market": "Migros"
    },
    {
        "name": "Migros Lavabo Açıcı 3x75 G",
        "url": "https://www.migros.com.tr/migros-lavabo-acici-3x75-g-p-1e2418a",
        "price": "34,95 TL",
        "market": "Migros"
    },
    {
        "name": "Domestos Yoğun Kıvamlı Çamaşır Suyu Dağ Esintisi 750 ml",
        "url": "https://www.migros.com.tr/domestos-yogun-kivamli-camasir-suyu-dag-esintisi-750-ml-p-1d25103",
        "price": "57,95 TL",
        "market": "Migros"
    },
    {
        "name": "OFF! Aqua Pump Losyon Spray 100 Ml",
        "url": "https://www.migros.com.tr/off-aqua-pump-losyon-spray-100-ml-p-1e16e19",
        "price": "99,95 TL",
        "market": "Migros"
    },
    {
        "name": "Scotch Brite Mikrofiber Bez 3'lü",
        "url": "https://www.migros.com.tr/scotch-brite-mikrofiber-bez-3lu-p-1db84f1",
        "price": "154,95 TL",
        "market": "Migros"
    },
    {
        "name": "Pril Power Elde Yıkama Sıvı Bulaşık Deterjanı 5 Etki Limon 653 G",
        "url": "https://www.migros.com.tr/pril-power-elde-yikama-sivi-bulasik-deterjani-5-etki-limon-653-g-p-1d31701",
        "price": "66,95 TL",
        "market": "Migros"
    },
    {
        "name": "Parex Klasik Yeşil Düz Sünger 5'li Eko Paket",
        "url": "https://www.migros.com.tr/parex-klasik-yesil-duz-sunger-5li-eko-paket-p-1dbab10",
        "price": "79,95 TL",
        "market": "Migros"
    },
    {
        "name": "Perwoll Siyah Sıvı Deterjan 2.97 L",
        "url": "https://www.migros.com.tr/perwoll-siyah-sivi-deterjan-297-l-p-1d1d9dc",
        "price": "280,95 TL",
        "market": "Migros"
    },
    {
        "name": "Migros Temizlik Bezi 5'li",
        "url": "https://www.migros.com.tr/migros-temizlik-bezi-5li-p-1db84e2",
        "price": "Fiyat bulunamadı",
        "market": "Migros"
    },
    {
        "name": "Porçöz Lavabo Açıcı Granül 2x50 G",
        "url": "https://www.migros.com.tr/porcoz-lavabo-acici-granul-2x50-g-p-1e241bc",
        "price": "54,95 TL",
        "market": "Migros"
    },
    {
        "name": "Cif Krem Yüzey Temizleyici Altın Işıltısı Amber Kokulu 750 Ml",
        "url": "https://www.migros.com.tr/cif-krem-yuzey-temizleyici-altin-isiltisi-amber-kokulu-750-ml-p-1d7cd56",
        "price": "79,95 TL",
        "market": "Migros"
    },
    {
        "name": "Cif Ultra Hız & Güç Yağ Çözücü Sprey Leke ve Kir Çıkarıcı Mutfak 1000 ML",
        "url": "https://www.migros.com.tr/cif-ultra-hiz-guc-yag-cozucu-sprey-leke-ve-kir-cikarici-mutfak-1000-ml-p-1d4f3a1",
        "price": "86,95 TL",
        "market": "Migros"
    },
    {
        "name": "Migros Bulaşık Makinesi Tuzu 2 Kg",
        "url": "https://www.migros.com.tr/migros-bulasik-makinesi-tuzu-2-kg-p-1d081a7",
        "price": "30,95 TL",
        "market": "Migros"
    },
    {
        "name": "Dixi Bref Çam Yüzey Temizleyici 2.5L",
        "url": "https://www.migros.com.tr/dixi-bref-cam-yuzey-temizleyici-25l-p-1d498f9",
        "price": "115,95 TL",
        "market": "Migros"
    },
    {
        "name": "Dixi Bref Gül Yüzey Temizleyici 2.5 L",
        "url": "https://www.migros.com.tr/dixi-bref-gul-yuzey-temizleyici-25-l-p-1d498f5",
        "price": "115,95 TL",
        "market": "Migros"
    },
    {
        "name": "Cif Jel Yüzey Temizleyici Cleanboost Tüm Yüzeyler İçin Leke Çıkarıcı Çamaşır Sulu Çiçek Ferahlığı 750 ML",
        "url": "https://www.migros.com.tr/cif-jel-yuzey-temizleyici-cleanboost-tum-yuzeyler-icin-leke-cikarici-camasir-sulu-cicek-ferahligi-750-ml-p-1d4c235",
        "price": "85,95 TL",
        "market": "Migros"
    },
    {
        "name": "Pril Elde Yıkama Sıvı Bulaşık Deterjanı 750ml Losyon Aloe Vera",
        "url": "https://www.migros.com.tr/pril-elde-yikama-sivi-bulasik-deterjani-750ml-losyon-aloe-vera-p-1d33884",
        "price": "66,95 TL",
        "market": "Migros"
    },
    {
        "name": "Ariel Dağ Esintisi Renklilere Özel Toz Çamaşır Deterjanı 7 Kg 46 Yıkama",
        "url": "https://www.migros.com.tr/ariel-dag-esintisi-renklilere-ozel-toz-camasir-deterjani-7-kg-46-yikama-p-1cbc700",
        "price": "454,95 TL",
        "market": "Migros"
    },
    {
        "name": "Ariel Dağ Esintisi Renkliler Toz Çamaşır Deterjanı 3 Kg 20 Yıkama",
        "url": "https://www.migros.com.tr/ariel-dag-esintisi-renkliler-toz-camasir-deterjani-3-kg-20-yikama-p-1cbc713",
        "price": "239,95 TL",
        "market": "Migros"
    },
    {
        "name": "Mr. Muscle KLOZET BLOK MARİNE 2'Lİ 77.2 G",
        "url": "https://www.migros.com.tr/mr-muscle-klozet-blok-marine-2li-772-g-p-1ddc0f1",
        "price": "99,95 TL",
        "market": "Migros"
    },
    {
        "name": "Peros Limon Sıvı Bulaşık Deterjanı 3.88 L",
        "url": "https://www.migros.com.tr/peros-limon-sivi-bulasik-deterjani-388-l-p-1d33880",
        "price": "149,95 TL",
        "market": "Migros"
    },
    {
        "name": "Porçöz Fırın Temizleyici Sprey 750 Ml",
        "url": "https://www.migros.com.tr/porcoz-firin-temizleyici-sprey-750-ml-p-1ddc177",
        "price": "99,95 TL",
        "market": "Migros"
    },
    {
        "name": "Porçöz Leke Çıkarıcı Sprey 750 Ml",
        "url": "https://www.migros.com.tr/porcoz-leke-cikarici-sprey-750-ml-p-1ddc0fb",
        "price": "114,95 TL",
        "market": "Migros"
    },
    {
        "name": "Cif Sprey Power & Shine Mutfak 750 Ml",
        "url": "https://www.migros.com.tr/cif-sprey-power-shine-mutfak-750-ml-p-1d4f3b4",
        "price": "114,95 TL",
        "market": "Migros"
    },
    {
        "name": "Domestos Çam Ferahlığı Çamaşır Suyu 5 L",
        "url": "https://www.migros.com.tr/domestos-cam-ferahligi-camasir-suyu-5-l-p-1d27515",
        "price": "184,95 TL",
        "market": "Migros"
    },
    {
        "name": "Banvit Piliç Bonfile Kg",
        "url": "https://www.migros.com.tr/banvit-pilic-bonfile-kg-p-2be844b",
        "price": "269,95 TL",
        "market": "Migros"
    },
    {
        "name": "Banvit Piliç Yaprak Döner 200 G",
        "url": "https://www.migros.com.tr/banvit-pilic-yaprak-doner-200-g-p-2be83f7",
        "price": "Fiyat bulunamadı",
        "market": "Migros"
    },
    {
        "name": "Dana Kıymalık Kg",
        "url": "https://www.migros.com.tr/dana-kiymalik-kg-p-17d9f99",
        "price": "539,95 TL",
        "market": "Migros"
    },
    {
        "name": "Namet Hindi Füme 7/24 60 G",
        "url": "https://www.migros.com.tr/namet-hindi-fume-724-60-g-p-e35f61",
        "price": "22,50 TL",
        "market": "Migros"
    },
    {
        "name": "Banvit Piliç Baget Kg",
        "url": "https://www.migros.com.tr/banvit-pilic-baget-kg-p-2be844f",
        "price": "139,95 TL",
        "market": "Migros"
    },
    {
        "name": "Uzman Kasap Dana Kıyma 400 G",
        "url": "https://www.migros.com.tr/uzman-kasap-dana-kiyma-400-g-p-17deed0",
        "price": "189,00 TL",
        "market": "Migros"
    },
    {
        "name": "Bolca Hindi Göğüs Bütün Fileto 750 G",
        "url": "https://www.migros.com.tr/bolca-hindi-gogus-butun-fileto-750-g-p-cafbf3",
        "price": "284,95 TL",
        "market": "Migros"
    },
    {
        "name": "Namet Pişmiş Döner 250 G",
        "url": "https://www.migros.com.tr/namet-pismis-doner-250-g-p-1853cbf",
        "price": "185,95 TL",
        "market": "Migros"
    },
    {
        "name": "Namet 7 / 24 Hindi Salam 60 G",
        "url": "https://www.migros.com.tr/namet-7-24-hindi-salam-60-g-p-d749eb",
        "price": "19,80 TL",
        "market": "Migros"
    },
    {
        "name": "Dana Kıymalık Yöresel Kg",
        "url": "https://www.migros.com.tr/dana-kiymalik-yoresel-kg-p-17da1d4",
        "price": "579,95 TL",
        "market": "Migros"
    },
    {
        "name": "Banvit Piliç Pirzola Kg",
        "url": "https://www.migros.com.tr/banvit-pilic-pirzola-kg-p-2be8451",
        "price": "129,95 TL",
        "market": "Migros"
    },
    {
        "name": "Bolca Hindi Sote But 750 G",
        "url": "https://www.migros.com.tr/bolca-hindi-sote-but-750-g-p-cafc01",
        "price": "382,95 TL",
        "market": "Migros"
    },
    {
        "name": "Uzman Kasap Izgara Köfte 320 G",
        "url": "https://www.migros.com.tr/uzman-kasap-izgara-kofte-320-g-p-17dee09",
        "price": "165,95 TL",
        "market": "Migros"
    },
    {
        "name": "Polonez Fit Yaşam XL Hindi Füme 150 G",
        "url": "https://www.migros.com.tr/polonez-fit-yasam-xl-hindi-fume-150-g-p-e35f89",
        "price": "99,00 TL",
        "market": "Migros"
    },
    {
        "name": "Uzman Kasap Dana Kuzu Kıyma 400 G",
        "url": "https://www.migros.com.tr/uzman-kasap-dana-kuzu-kiyma-400-g-p-17deecc",
        "price": "Fiyat bulunamadı",
        "market": "Migros"
    },
    {
        "name": "Pınar Aç Bitir Hindi Salam Taze Dilimlenmiş 10 Dilim 75 G",
        "url": "https://www.migros.com.tr/pinar-ac-bitir-hindi-salam-taze-dilimlenmis-10-dilim-75-g-p-d749cc",
        "price": "35,25 TL",
        "market": "Migros"
    },
    {
        "name": "Dana Kuzu Kıymalık Kg",
        "url": "https://www.migros.com.tr/dana-kuzu-kiymalik-kg-p-17da180",
        "price": "539,95 TL",
        "market": "Migros"
    },
    {
        "name": "Banvit Piliç Kanat Kg",
        "url": "https://www.migros.com.tr/banvit-pilic-kanat-kg-p-2be842d",
        "price": "244,95 TL",
        "market": "Migros"
    },
    {
        "name": "Uzman Kasap Tekirdağ Köfte 320 G",
        "url": "https://www.migros.com.tr/uzman-kasap-tekirdag-kofte-320-g-p-17dee1f",
        "price": "165,95 TL",
        "market": "Migros"
    },
    {
        "name": "Beypiliç Parmak Bonfile Kg",
        "url": "https://www.migros.com.tr/beypilic-parmak-bonfile-kg-p-c6a972",
        "price": "184,95 TL",
        "market": "Migros"
    },
    {
        "name": "Banvit Piliç Schnitzel 700 G",
        "url": "https://www.migros.com.tr/banvit-pilic-schnitzel-700-g-p-2be83f6",
        "price": "119,95 TL",
        "market": "Migros"
    },
    {
        "name": "Banvit Jumbo Sosis 330 G",
        "url": "https://www.migros.com.tr/banvit-jumbo-sosis-330-g-p-ce0849",
        "price": "73,90 TL",
        "market": "Migros"
    },
    {
        "name": "Erşan Pişmiş Dana Döner 250 G",
        "url": "https://www.migros.com.tr/ersan-pismis-dana-doner-250-g-p-17dee21",
        "price": "159,95 TL",
        "market": "Migros"
    },
    {
        "name": "Banvit Piliç Nugget 700 G",
        "url": "https://www.migros.com.tr/banvit-pilic-nugget-700-g-p-2be83f5",
        "price": "117,95 TL",
        "market": "Migros"
    },
    {
        "name": "Banvit Piliç Izgara Tava Kg",
        "url": "https://www.migros.com.tr/banvit-pilic-izgara-tava-kg-p-2be8425",
        "price": "299,95 TL",
        "market": "Migros"
    },
    {
        "name": "Dana But Sotelik Et Yöresel Kg",
        "url": "https://www.migros.com.tr/dana-but-sotelik-et-yoresel-kg-p-17da1ee",
        "price": "769,95 TL",
        "market": "Migros"
    },
    {
        "name": "Dana Antrikot Çiftlik Kg",
        "url": "https://www.migros.com.tr/dana-antrikot-ciftlik-kg-p-17d9f5b",
        "price": "969,95 TL",
        "market": "Migros"
    },
    {
        "name": "Bolca Tabaklı Alt But Kemiksiz Hindi 500 G",
        "url": "https://www.migros.com.tr/bolca-tabakli-alt-but-kemiksiz-hindi-500-g-p-cafbea",
        "price": "207,95 TL",
        "market": "Migros"
    },
    {
        "name": "Dana Ciğer Kg",
        "url": "https://www.migros.com.tr/dana-ciger-kg-p-18ce199",
        "price": "579,95 TL",
        "market": "Migros"
    },
    {
        "name": "Maret Dana Isıl İşlem Görmüş Afiyetle Sucuk 200 G",
        "url": "https://www.migros.com.tr/maret-dana-isil-islem-gormus-afiyetle-sucuk-200-g-p-d8ad5d",
        "price": "160,00 TL",
        "market": "Migros"
    },
    {
        "name": "Bolez Köylüm Poşetli Bütün Piliç Kg",
        "url": "https://www.migros.com.tr/bolez-koylum-posetli-butun-pilic-kg-p-c6cf9d",
        "price": "137,95 TL",
        "market": "Migros"
    },
    {
        "name": "Bolca Hindi Sote Göğüs 750 G",
        "url": "https://www.migros.com.tr/bolca-hindi-sote-gogus-750-g-p-cafbf2",
        "price": "284,95 TL",
        "market": "Migros"
    },
    {
        "name": "Dana Haşlamalık Gerdan Kg",
        "url": "https://www.migros.com.tr/dana-haslamalik-gerdan-kg-p-17da19c",
        "price": "Fiyat bulunamadı",
        "market": "Migros"
    },
    {
        "name": "Namet 7/24 Dana Macar Salam 60 G",
        "url": "https://www.migros.com.tr/namet-724-dana-macar-salam-60-g-p-d749e4",
        "price": "38,00 TL",
        "market": "Migros"
    },
    {
        "name": "Eral Dana Kokoreç Baharatlı 200 G (Kuşbaşı)",
        "url": "https://www.migros.com.tr/eral-dana-kokorec-baharatli-200-g-kusbasi-p-18ce1b7",
        "price": "199,95 TL",
        "market": "Migros"
    },
    {
        "name": "Namet Kangal Sucuk 240 G",
        "url": "https://www.migros.com.tr/namet-kangal-sucuk-240-g-p-d8d15c",
        "price": "310,00 TL",
        "market": "Migros"
    },
    {
        "name": "Kuzu Yemeklik Kuşbaşı Kg",
        "url": "https://www.migros.com.tr/kuzu-yemeklik-kusbasi-kg-p-17bf3cb",
        "price": "845,95 TL",
        "market": "Migros"
    },
    {
        "name": "Uzman Kasap Klasik Köfte 320 G",
        "url": "https://www.migros.com.tr/uzman-kasap-klasik-kofte-320-g-p-17dee0c",
        "price": "175,95 TL",
        "market": "Migros"
    },
    {
        "name": "Dana But Sotelik Et Çiftlik Kg",
        "url": "https://www.migros.com.tr/dana-but-sotelik-et-ciftlik-kg-p-17d9f68",
        "price": "649,95 TL",
        "market": "Migros"
    },
    {
        "name": "Çipura 400/600 Kg",
        "url": "https://www.migros.com.tr/cipura-400600-kg-p-121c7da",
        "price": "359,59 TL",
        "market": "Migros"
    },
    {
        "name": "Polonez Macar Salam 90 G",
        "url": "https://www.migros.com.tr/polonez-macar-salam-90-g-p-d74a69",
        "price": "112,50 TL",
        "market": "Migros"
    },
    {
        "name": "Dana İncik",
        "url": "https://www.migros.com.tr/dana-incik-p-17dc66e",
        "price": "Fiyat bulunamadı",
        "market": "Migros"
    },
    {
        "name": "Kuzu Gerdan Kg (Kemikli, Dilimli)",
        "url": "https://www.migros.com.tr/kuzu-gerdan-kg-kemikli-dilimli-p-16e5d38",
        "price": "559,95 TL",
        "market": "Migros"
    },
    {
        "name": "Polonez Dilimli Çemensiz Seçme Pastırma 100 G",
        "url": "https://www.migros.com.tr/polonez-dilimli-cemensiz-secme-pastirma-100-g-p-da56e5",
        "price": "149,00 TL",
        "market": "Migros"
    },
    {
        "name": "Dana Döş Rulo Yöresel Kg (Kıyma)",
        "url": "https://www.migros.com.tr/dana-dos-rulo-yoresel-kg-kiyma-p-17da1d6",
        "price": "579,95 TL",
        "market": "Migros"
    },
    {
        "name": "Bolca Hindi Külbastı 500 G",
        "url": "https://www.migros.com.tr/bolca-hindi-kulbasti-500-g-p-cafc00",
        "price": "169,95 TL",
        "market": "Migros"
    },
    {
        "name": "Banvit Piliç Kokteyl Sosis 1000 G",
        "url": "https://www.migros.com.tr/banvit-pilic-kokteyl-sosis-1000-g-p-d74a56",
        "price": "129,00 TL",
        "market": "Migros"
    },
    {
        "name": "Kuzu Külbastı Kg (But Eti, Kemiksiz, Dilimli)",
        "url": "https://www.migros.com.tr/kuzu-kulbasti-kg-but-eti-kemiksiz-dilimli-p-16e5d2a",
        "price": "999,95 TL",
        "market": "Migros"
    },
    {
        "name": "Banvit Piliç Nugget 300 G",
        "url": "https://www.migros.com.tr/banvit-pilic-nugget-300-g-p-ce0839",
        "price": "54,95 TL",
        "market": "Migros"
    },
    {
        "name": "Uzman Kasap Kuzu Sac Kavurmalık 400 G",
        "url": "https://www.migros.com.tr/uzman-kasap-kuzu-sac-kavurmalik-400-g-p-17def27",
        "price": "199,95 TL",
        "market": "Migros"
    },
    {
        "name": "Dardanel Fish Finger 400 G",
        "url": "https://www.migros.com.tr/dardanel-fish-finger-400-g-p-10b0b69",
        "price": "159,95 TL",
        "market": "Migros"
    },
    {
        "name": "Başyazıcıoğlu İnan Dana Kavurma 150G",
        "url": "https://www.migros.com.tr/basyazicioglu-inan-dana-kavurma-150g-p-dbd970",
        "price": "135,00 TL",
        "market": "Migros"
    },
    {
        "name": "Altın Dana Dana Kavurma 150G",
        "url": "https://www.migros.com.tr/altin-dana-dana-kavurma-150g-p-dbd975",
        "price": "Fiyat bulunamadı",
        "market": "Migros"
    },
    {
        "name": "Maret 10'lu Sosis 432 G",
        "url": "https://www.migros.com.tr/maret-10lu-sosis-432-g-p-d5c6a3",
        "price": "369,00 TL",
        "market": "Migros"
    },
    {
        "name": "Bolez Köylüm Kanat Kg",
        "url": "https://www.migros.com.tr/bolez-koylum-kanat-kg-p-c6a989",
        "price": "199,95 TL",
        "market": "Migros"
    },
    {
        "name": "Migros Hindi Füme Eti 90 G",
        "url": "https://www.migros.com.tr/migros-hindi-fume-eti-90-g-p-e35b70",
        "price": "34,75 TL",
        "market": "Migros"
    },
    {
        "name": "Maret Hindi Füme 110 G",
        "url": "https://www.migros.com.tr/maret-hindi-fume-110-g-p-e35f5c",
        "price": "66,90 TL",
        "market": "Migros"
    },
    {
        "name": "Gedik Piliç Salamlı Cordon Bleu 285G",
        "url": "https://www.migros.com.tr/gedik-pilic-salamli-cordon-bleu-285g-p-ce231e",
        "price": "70,95 TL",
        "market": "Migros"
    },
    {
        "name": "Bolez Köylüm Baget Kg",
        "url": "https://www.migros.com.tr/bolez-koylum-baget-kg-p-c6a988",
        "price": "129,95 TL",
        "market": "Migros"
    },
    {
        "name": "Migros %3 Yağlı Uht Süt 1 L",
        "url": "https://www.migros.com.tr/migros-3-yagli-uht-sut-1-l-p-a805c0",
        "price": "33,95 TL",
        "market": "Migros"
    },
    {
        "name": "Pınar Süt 1 L",
        "url": "https://www.migros.com.tr/pinar-sut-1-l-p-a7ffda",
        "price": "49,95 TL",
        "market": "Migros"
    },
    {
        "name": "Migros Yarım Yağlı Uht Süt 1 L",
        "url": "https://www.migros.com.tr/migros-yarim-yagli-uht-sut-1-l-p-a805ad",
        "price": "Fiyat bulunamadı",
        "market": "Migros"
    },
    {
        "name": "Güres M - Orta Boy Yumurta 30'lu ( 53 - 62 G)",
        "url": "https://www.migros.com.tr/gures-m-orta-boy-yumurta-30lu-53-62-g-p-1312df3",
        "price": "172,25 TL",
        "market": "Migros"
    },
    {
        "name": "Altınkılıç Tam Yağlı Olgunlaştırılmış İnek Peyniri 500 G",
        "url": "https://www.migros.com.tr/altinkilic-tam-yagli-olgunlastirilmis-inek-peyniri-500-g-p-98e101",
        "price": "239,90 TL",
        "market": "Migros"
    },
    {
        "name": "Migros Tam Yağlı Homojenize Yoğurt 3000 G",
        "url": "https://www.migros.com.tr/migros-tam-yagli-homojenize-yogurt-3000-g-p-bec3c5",
        "price": "Fiyat bulunamadı",
        "market": "Migros"
    },
    {
        "name": "Migros Tam Yağlı Homojenize Yoğurt 1500 G",
        "url": "https://www.migros.com.tr/migros-tam-yagli-homojenize-yogurt-1500-g-p-bec3c4",
        "price": "66,50 TL",
        "market": "Migros"
    },
    {
        "name": "Sütaş Kaymaksız Yoğurt 1000 G",
        "url": "https://www.migros.com.tr/sutas-kaymaksiz-yogurt-1000-g-p-bebd9c",
        "price": "57,50 TL",
        "market": "Migros"
    },
    {
        "name": "İçim Şef %18 Yağlı Krema 200 Ml",
        "url": "https://www.migros.com.tr/icim-sef-18-yagli-krema-200-ml-p-b047a3",
        "price": "39,90 TL",
        "market": "Migros"
    },
    {
        "name": "Pınar Denge Laktozsuz Süt 1 L",
        "url": "https://www.migros.com.tr/pinar-denge-laktozsuz-sut-1-l-p-a80029",
        "price": "57,95 TL",
        "market": "Migros"
    },
    {
        "name": "Tire Organik Yumurta 10'lu M Boy (53-62 G)",
        "url": "https://www.migros.com.tr/tire-organik-yumurta-10lu-m-boy-53-62-g-p-13134c3",
        "price": "119,95 TL",
        "market": "Migros"
    },
    {
        "name": "Migros %3 Yağlı Yüksek Sıcaklıkta Pastörize Süt 1 L",
        "url": "https://www.migros.com.tr/migros-3-yagli-yuksek-sicaklikta-pastorize-sut-1-l-p-a807c7",
        "price": "38,75 TL",
        "market": "Migros"
    },
    {
        "name": "İçim Taze Kaşar Peyniri 700 G",
        "url": "https://www.migros.com.tr/icim-taze-kasar-peyniri-700-g-p-9a3ee7",
        "price": "327,90 TL",
        "market": "Migros"
    },
    {
        "name": "Migros İnek Peyniri 600G",
        "url": "https://www.migros.com.tr/migros-inek-peyniri-600g-p-98e14d",
        "price": "168,75 TL",
        "market": "Migros"
    },
    {
        "name": "Tahsildaroğlu Torba Lor Peyniri 350 G",
        "url": "https://www.migros.com.tr/tahsildaroglu-torba-lor-peyniri-350-g-p-9ebe40",
        "price": "49,90 TL",
        "market": "Migros"
    },
    {
        "name": "Nutella Kakaolu Fındık Kreması 750 G",
        "url": "https://www.migros.com.tr/nutella-kakaolu-findik-kremasi-750-g-p-6d2ffd",
        "price": "180,95 TL",
        "market": "Migros"
    },
    {
        "name": "Eker Kaymaklı Tava Yoğurt 1 Kg",
        "url": "https://www.migros.com.tr/eker-kaymakli-tava-yogurt-1-kg-p-bec383",
        "price": "86,50 TL",
        "market": "Migros"
    },
    {
        "name": "Bahçıvan Süzme Peynir 500 G",
        "url": "https://www.migros.com.tr/bahcivan-suzme-peynir-500-g-p-98c9b7",
        "price": "127,90 TL",
        "market": "Migros"
    },
    {
        "name": "Ünal Lüks Klasik İnek Peyniri Kg",
        "url": "https://www.migros.com.tr/unal-luks-klasik-inek-peyniri-kg-p-98d987",
        "price": "425,00 TL",
        "market": "Migros"
    },
    {
        "name": "Naturaköy Gezen 15'li Yumurta M Orta Boy (53-62) G",
        "url": "https://www.migros.com.tr/naturakoy-gezen-15li-yumurta-m-orta-boy-53-62-g-p-2bebb85",
        "price": "134,95 TL",
        "market": "Migros"
    },
    {
        "name": "İçim Rahat Laktozsuz Süt 1 L",
        "url": "https://www.migros.com.tr/icim-rahat-laktozsuz-sut-1-l-p-a80012",
        "price": "49,50 TL",
        "market": "Migros"
    },
    {
        "name": "Bahçıvan Hellim Peyniri 225 G",
        "url": "https://www.migros.com.tr/bahcivan-hellim-peyniri-225-g-p-9ed4cc",
        "price": "171,50 TL",
        "market": "Migros"
    },
    {
        "name": "Migros Yarım Yağlı Laktozsuz Uht Süt 1 L",
        "url": "https://www.migros.com.tr/migros-yarim-yagli-laktozsuz-uht-sut-1-l-p-a80077",
        "price": "39,95 TL",
        "market": "Migros"
    },
    {
        "name": "Bahçıvan Çeçil Peyniri 200 G",
        "url": "https://www.migros.com.tr/bahcivan-cecil-peyniri-200-g-p-9ecb9f",
        "price": "146,50 TL",
        "market": "Migros"
    },
    {
        "name": "Migros Tereyağı 250 G",
        "url": "https://www.migros.com.tr/migros-tereyagi-250-g-p-b75d83",
        "price": "Fiyat bulunamadı",
        "market": "Migros"
    },
    {
        "name": "Pınar Süzme Peynir 500 G",
        "url": "https://www.migros.com.tr/pinar-suzme-peynir-500-g-p-98e0ec",
        "price": "130,00 TL",
        "market": "Migros"
    },
    {
        "name": "Bahçıvan Mozzarella Peyniri Rende 200 G",
        "url": "https://www.migros.com.tr/bahcivan-mozzarella-peyniri-rende-200-g-p-9a24e3",
        "price": "137,90 TL",
        "market": "Migros"
    },
    {
        "name": "Torku Süt 4X1 L",
        "url": "https://www.migros.com.tr/torku-sut-4x1-l-p-a82681",
        "price": "198,00 TL",
        "market": "Migros"
    },
    {
        "name": "Tahsildaroğlu Taze Tam Yağlı Dil Peyniri 200 G",
        "url": "https://www.migros.com.tr/tahsildaroglu-taze-tam-yagli-dil-peyniri-200-g-p-9a1d3b",
        "price": "107,50 TL",
        "market": "Migros"
    },
    {
        "name": "Sütaş Süzme Yoğurt 750 G",
        "url": "https://www.migros.com.tr/sutas-suzme-yogurt-750-g-p-bebda2",
        "price": "106,40 TL",
        "market": "Migros"
    }
]